LICENSE
MANIFEST.in
README.md
pyproject.toml
setup.cfg
setup.py
algeria_cities/__init__.py
algeria_cities/admin.py
algeria_cities/apps.py
algeria_cities/models.py
algeria_cities/tests.py
algeria_cities/views.py
algeria_cities/fixtures/data.json
algeria_cities/migrations/0001_initial.py
algeria_cities/migrations/0002_load_data.py
algeria_cities/migrations/__init__.py
django_algeria_cities.egg-info/PKG-INFO
django_algeria_cities.egg-info/SOURCES.txt
django_algeria_cities.egg-info/dependency_links.txt
django_algeria_cities.egg-info/requires.txt
django_algeria_cities.egg-info/top_level.txt