Metadata-Version: 2.2
Name: django-algeria-cities
Version: 0.1
Summary: Django package provides a complete list of all administrative provinces and cities in Algeria.
Home-page: https://github.com/tarek-berkane/algeria-cities-django
Author: Tarek Berkane
Author-email: tarekg320@gmail.com
License: MIT
Classifier: Programming Language :: Python :: 3
Classifier: Programming Language :: Python :: 3.8
Classifier: Programming Language :: Python :: 3.9
Classifier: Programming Language :: Python :: 3.10
Classifier: Programming Language :: Python :: 3.11
Classifier: Framework :: Django
Classifier: Framework :: Django :: 4.2
Classifier: Framework :: Django :: 5.0
Classifier: Framework :: Django :: 5.1
Classifier: License :: OSI Approved :: MIT License
Classifier: Operating System :: OS Independent
Classifier: Intended Audience :: Developers
Classifier: Topic :: Software Development :: Libraries :: Python Modules
Classifier: Topic :: Database
Classifier: Natural Language :: French
Classifier: Natural Language :: Arabic
Requires-Python: >=3.8
License-File: LICENSE
Requires-Dist: Django>=4.2
